single_kernel_mongo/__init__.py
single_kernel_mongo/abstract_charm.py
single_kernel_mongo/config/__init__.py
single_kernel_mongo/config/literals.py
single_kernel_mongo/config/models.py
single_kernel_mongo/config/relations.py
single_kernel_mongo/config/statuses.py
single_kernel_mongo/core/__init__.py
single_kernel_mongo/core/abstract_upgrades_v3.py
single_kernel_mongo/core/k8s_workload.py
single_kernel_mongo/core/kubernetes_upgrades_v3.py
single_kernel_mongo/core/machine_upgrades_v3.py
single_kernel_mongo/core/operator.py
single_kernel_mongo/core/secrets.py
single_kernel_mongo/core/structured_config.py
single_kernel_mongo/core/version_checker.py
single_kernel_mongo/core/vm_workload.py
single_kernel_mongo/core/workload.py
single_kernel_mongo/events/__init__.py
single_kernel_mongo/events/backups.py
single_kernel_mongo/events/cluster.py
single_kernel_mongo/events/database.py
single_kernel_mongo/events/ldap.py
single_kernel_mongo/events/lifecycle.py
single_kernel_mongo/events/primary_action.py
single_kernel_mongo/events/sharding.py
single_kernel_mongo/events/tls.py
single_kernel_mongo/exceptions.py
single_kernel_mongo/lib/charms/certificate_transfer_interface/v0/certificate_transfer.py
single_kernel_mongo/lib/charms/data_platform_libs/v0/data_interfaces.py
single_kernel_mongo/lib/charms/data_platform_libs/v0/s3.py
single_kernel_mongo/lib/charms/glauth_k8s/v0/ldap.py
single_kernel_mongo/lib/charms/grafana_agent/v0/cos_agent.py
single_kernel_mongo/lib/charms/grafana_k8s/v0/grafana_dashboard.py
single_kernel_mongo/lib/charms/loki_k8s/v0/loki_push_api.py
single_kernel_mongo/lib/charms/operator_libs_linux/v0/sysctl.py
single_kernel_mongo/lib/charms/operator_libs_linux/v1/systemd.py
single_kernel_mongo/lib/charms/operator_libs_linux/v2/snap.py
single_kernel_mongo/lib/charms/prometheus_k8s/v0/prometheus_scrape.py
single_kernel_mongo/lib/charms/tls_certificates_interface/v4/tls_certificates.py
single_kernel_mongo/managers/__init__.py
single_kernel_mongo/managers/backups.py
mongo_charms_single_kernel-1.8.23.dist-info/METADATA
mongo_charms_single_kernel-1.8.23.dist-info/WHEEL
mongo_charms_single_kernel-1.8.23.dist-info/licenses/LICENSE
mongo_charms_single_kernel-1.8.23.dist-info/RECORD
