Metadata-Version: 2.4
Name: mongo-charms-single-kernel
Version: 1.8.23
Summary: Shared and reusable code for Mongo-related charms
License-Expression: Apache-2.0
License-File: LICENSE
Author: Neha Oudin
Author-email: neha@oudin.red
Requires-Python: >=3.10,<4.0
Classifier: Development Status :: 3 - Alpha
Classifier: Intended Audience :: Developers
Classifier: Intended Audience :: System Administrators
Classifier: Operating System :: POSIX :: Linux
Requires-Dist: boto3 (>=1.37.12,<1.38.0)
Requires-Dist: charm-refresh (>=3.1.0.2,<4.0.0.0)
Requires-Dist: cosl
Requires-Dist: cryptography
Requires-Dist: dacite (>=1.9.0,<1.10.0)
Requires-Dist: data-platform-helpers (>=0.1.7)
Requires-Dist: deepmerge (>=2.0)
Requires-Dist: jinja2
Requires-Dist: jsonschema (>=4.24.0,<4.25.0)
Requires-Dist: lightkube
Requires-Dist: mypy-boto3-s3 (>=1.37.0,<1.38.0)
Requires-Dist: ops (>=2.21.1,<2.22.0)
Requires-Dist: overrides (>=7.7.0,<7.8.0)
Requires-Dist: poetry-core (>=2.0)
Requires-Dist: pydantic (>=2.11.0,<2.12.0)
Requires-Dist: pydantic-settings
Requires-Dist: pymongo
Requires-Dist: python-ldap
Requires-Dist: pyyaml (>=6.0.2,<6.1.0)
Requires-Dist: tenacity (>=9.0.0,<9.1.0)
Project-URL: Bug Tracker, https://github.com/canonical/mongo-single-kernel-library/issues
Project-URL: Contribute, https://github.com/canonical/mongo-single-kernel-library/blob/main/CONTRIBUTING.md
Project-URL: Homepage, https://github.com/canonical/mongo-single-kernel-library
Project-URL: Matrix, https://matrix.to/#/#charmhub-data-platform:ubuntu.com
Project-URL: Repository, https://github.com/canonical/mongo-single-kernel-library
